Getting started with FPGAs/project_4/verilog/debounce_filter.sv
module Debounce_Filter #(
    parameter DEBOUNCE_LIMIT = 20
) (
    input  i_clk,
    input  i_bouncy,
    output o_debounced
);

  reg [$clog2(DEBOUNCE_LIMIT)-1:0] r_count = 0;
  reg r_state = 1'b0;

  always @(posedge i_clk) begin
    if (i_bouncy !== r_state && r_count < DEBOUNCE_LIMIT - 1) begin
      r_count <= r_count + 1;
    end else if (r_count == DEBOUNCE_LIMIT - 1) begin
      r_state <= i_bouncy;
      r_count <= 0;
    end else begin
      r_count <= 0;
    end
  end

  assign o_debounced = r_state;
endmodule

Getting started with FPGAs/project_4/debounce_filter_tb.sv
module Debounce_Filter_TB ();
  reg r_clk = 1'b0;
  reg r_bouncy = 1'b0;

  always #2 r_clk <= !r_clk;

  Debounce_Filter #(
      .DEBOUNCE_LIMIT(4)
  ) UUT (
      .i_clk(r_clk),
      .i_bouncy(r_bouncy),
      .o_debounced(w_debounced)
  );

  initial begin
    $dumpfile("dump.vcd");

    repeat (3) @(posedge r_clk);
    r_bouncy <= 1'b1;


    @(posedge r_clk);
    r_bouncy <= 1'b0;  // simulate glitch/bounce of switch

    @(posedge r_clk);
    r_bouncy <= 1'b1;


    repeat (6) @(posedge r_clk);
    $display("Test Completed");
    $finish();
  end
endmodule

Getting started with FPGAs/project_4/vivado/vivado.sim/sim_1/behav/xsim/dump.vcd
$date
   Fri Nov  8 20:43:03 2024
$end

$version
  2024.1
  $dumpfile ("dump.vcd") 
$end

$timescale
  1ps
$end

$scope module Debounce_Filter_TB $end
$var reg 1 ! r_clk $end
$var reg 1 " r_bouncy $end
$var wire 1 # w_debounced $end
$scope module UUT $end
$var wire 1 $ i_clk $end
$var wire 1 % i_bouncy $end
$var wire 1 # o_debounced $end
$var reg 2 & r_count [1:0] $end
$var reg 1 ' r_state $end
$upscope $end
$upscope $end
$enddefinitions $end

#0
$dumpvars
0!
0"
0#
0$
0%
b0 &
0'
$end

#2000
1!
1$

#4000
0!
0$

#6000
1!
1$

#8000
0!
0$

#10000
1!
1"
1$
1%

#12000
0!
0$

#14000
1!
0"
1$
0%
b1 &

#16000
0!
0$

#18000
1!
1"
1$
1%
b0 &

#20000
0!
0$

#22000
1!
1$
b1 &

#24000
0!
0$

#26000
1!
1$
b10 &

#28000
0!
0$

#30000
1!
1$
b11 &

#32000
0!
0$

#34000
1!
1#
1$
b0 &
1'

